Workbook
Name Anos: Calculadora!$D$13
Name Aporte: Calculadora!$D$12
Name DivMensais: Calculadora!$D$16
Name RendCarteira: Calculadora!$D$8
Name Salario: Calculadora!$D$7
Name Sugestao_Invest: Calculadora!$D$9
Name SugestInvest: Calculadora!$D$9
Name Taxa: Calculadora!$D$14

Sheet Calculadora
B6: CONFIGURAÇÕES
B7: Salário | D7: 2309
B8: Rendimento Carteira | D8: 0.01
B9: Sugestão de investimento (30%) | D9: =Salario*30% -> 692.7
B11: INVESTIMENTO MENSAL
B12: Quanto investir por mês ? | D12: =SugestInvest -> 692.7
B13: Por quantos anos ? | D13: 5
B14: Taxa de rendimento mensal ? | D14: 0.01079
B15: Patrimônio acumulado ? | D15: =FV(Taxa,Anos*12,D12*(-1)) -> 58032.268
B16: Dividendo mensais ? | D16: =$D$15*D14 -> 626.16818
B18: CENÁRIOS | D18: Dividendos
A19: 2 | B19: Quanto em 2 anos ? | C19: =FV(Taxa,$A19*12,$D$12*(-1)) -> 18860.577 | D19: =C19*Taxa -> 203.50563
A20: 5 | B20: Quanto em 5 anos ? | C20: =FV(Taxa,$A20*12,$D$12*(-1)) -> 58032.268 | D20: =C20*Taxa -> 626.16818
A21: 10 | B21: Quanto em 10 anos ? | C21: =FV(Taxa,$A21*12,$D$12*(-1)) -> 168522.97 | D21: =C21*Taxa -> 1818.3629
A22: 15 | B22: Quanto em 15 anos ? | C22: =FV(Taxa,$A22*12,$D$12*(-1)) -> 378892.07 | D22: =C22*Taxa -> 4088.2455
A23: 20 | B23: Quanto em 20 anos ? | C23: =FV(Taxa,$A23*12,$D$12*(-1)) -> 779424.93 | D23: =C23*Taxa -> 8409.995
A24: 25 | B24: Quanto em 25 anos ? | C24: =FV(Taxa,$A24*12,$D$12*(-1)) -> 1542020.6 | D24: =C24*Taxa -> 16638.403
A25: 30 | B25: Quanto em 30 anos ? | C25: =FV(Taxa,$A25*12,$D$12*(-1)) -> 2993966.9 | D25: =C25*Taxa -> 32304.903
A26: 35 | B26: Quanto em 35 anos ? | C26: =FV(Taxa,$A26*12,$D$12*(-1)) -> 5758404.3 | D26: =C26*Taxa -> 62133.182
B28: Perfil | D28: Conservador
B29: Valor a ser investido por mês | D29: =Aporte -> 692.7
B31: Tipo de FII | C31: % Sugerido | D31: Valores
B32: Papel | C32: =VLOOKUP($D$28&"-"&B32,Tb_Apoio!$A:$D,4,FALSE) -> 0.3 | D32: =$D$29*C32 -> 207.81
B33: Tijolo | C33: =VLOOKUP($D$28&"-"&B33,Tb_Apoio!$A:$D,4,FALSE) -> 0.5 | D33: =$D$29*C33 -> 346.35
B34: Híbridos | C34: =VLOOKUP($D$28&"-"&B34,Tb_Apoio!$A:$D,4,FALSE) -> 0.1 | D34: =$D$29*C34 -> 69.27
B35: FOFs | C35: =VLOOKUP($D$28&"-"&B35,Tb_Apoio!$A:$D,4,FALSE) -> 0.1 | D35: =$D$29*C35 -> 69.27
B36: Desenvolvimento | C36: =VLOOKUP($D$28&"-"&B36,Tb_Apoio!$A:$D,4,FALSE) -> 0 | D36: =$D$29*C36 -> 0
B37: Hotelarias | C37: =VLOOKUP($D$28&"-"&B37,Tb_Apoio!$A:$D,4,FALSE) -> 0 | D37: =$D$29*C37 -> 0
C38: =SUM(C32:C37) -> 1 | D38: =SUM(D32:D37) -> 692.7

Sheet Tb_Apoio
A4: Chave | B4: Perfil | C4: Tipo de FII | D4: % a Investir
A5: =B5&"-"&C5 -> Conservador-Papel | B5: Conservador | C5: Papel | D5: 0.3
A6: =B6&"-"&C6 -> Conservador-Tijolo | B6: Conservador | C6: Tijolo | D6: 0.5
A7: =B7&"-"&C7 -> Conservador-Híbridos | B7: Conservador | C7: Híbridos | D7: 0.1
A8: =B8&"-"&C8 -> Conservador-FOFs | B8: Conservador | C8: FOFs | D8: 0.1
A9: =B9&"-"&C9 -> Conservador-Desenvolvimento | B9: Conservador | C9: Desenvolvimento | D9: 0
A10: =B10&"-"&C10 -> Conservador-Hotelarias | B10: Conservador | C10: Hotelarias | D10: 0
A11: =B11&"-"&C11 -> Moderado-Papel | B11: Moderado | C11: Papel | D11: 0.32
A12: =B12&"-"&C12 -> Moderado-Tijolo | B12: Moderado | C12: Tijolo | D12: 0.35
A13: =B13&"-"&C13 -> Moderado-Híbridos | B13: Moderado | C13: Híbridos | D13: 0.08
A14: =B14&"-"&C14 -> Moderado-FOFs | B14: Moderado | C14: FOFs | D14: 0.05
A15: =B15&"-"&C15 -> Moderado-Desenvolvimento | B15: Moderado | C15: Desenvolvimento | D15: 0.1
A16: =B16&"-"&C16 -> Moderado-Hotelarias | B16: Moderado | C16: Hotelarias | D16: 0.1
... A22: =B22&"-"&C22 -> Agressivo-Hotelarias | B22: Agressivo | C22: Hotelarias | D22: 0.1
